iflow_mcp_cek_nomor_rekening_bank_indone-0.1.11.dist-info/licenses/LICENSE
mcp_gateway/__init__.py
mcp_gateway/__main__.py
mcp_gateway/loader.py
mcp_gateway/server.py
mcp_gateway/data/config.yaml
iflow_mcp_cek_nomor_rekening_bank_indone-0.1.11.dist-info/METADATA
iflow_mcp_cek_nomor_rekening_bank_indone-0.1.11.dist-info/WHEEL
iflow_mcp_cek_nomor_rekening_bank_indone-0.1.11.dist-info/entry_points.txt
iflow_mcp_cek_nomor_rekening_bank_indone-0.1.11.dist-info/top_level.txt
iflow_mcp_cek_nomor_rekening_bank_indone-0.1.11.dist-info/RECORD
