Metadata-Version: 2.4
Name: iflow-mcp-cek_nomor_rekening_bank_indone
Version: 0.1.11
Summary: Cek Nomor Rekening Semua Bank Indonesia
Requires-Python: >=3.10
License-File: LICENSE
Requires-Dist: mcp>=1.6.0
Requires-Dist: pyyaml>=6.0.2
Requires-Dist: jinja2>=3.0.0
Dynamic: license-file
